client/__init__.py
client/add_contact.py
client/client.py
client/client_db.py
client/client_engine.py
client/client_gui.py
client/decos.py
client/get_username.py
client/start_client.py
client/log/__init__.py
client/log/client_log_config.py
client/log/server_log_config.py
client/service/__init__.py
client/service/service.py
client/service/settings.ini
rtrv_my_chat_client-1.0.5.data/scripts/client_run
rtrv_my_chat_client-1.0.5.dist-info/METADATA
rtrv_my_chat_client-1.0.5.dist-info/WHEEL
rtrv_my_chat_client-1.0.5.dist-info/top_level.txt
rtrv_my_chat_client-1.0.5.dist-info/RECORD
