Metadata-Version: 2.1
Name: rtrv-my-chat-client
Version: 1.0.5
Summary: my_chat_client
Home-page: UNKNOWN
Author: RTretyakov
Author-email: rtretyakov@outlook.com
License: UNKNOWN
Platform: UNKNOWN
Requires-Dist: PyQt5
Requires-Dist: sqlalchemy
Requires-Dist: pycryptodome
Requires-Dist: pycryptodomex
